redux/__init__.py
redux/_internal/__init__.py
redux/_internal/action.py
redux/_internal/constants.py
redux/_internal/epic.py
redux/_internal/feature.py
redux/_internal/reducer.py
redux/_internal/selectors.py
redux/_internal/store.py
redux/_internal/types.py
tests/counter/__init__.py
tests/counter/action.py
tests/counter/constants.py
tests/counter/feature.py
tests/counter/reducer.py
tests/counter/test_counter.py
tests/feature/__init__.py
tests/feature/feature.py
tests/init/__init__.py
tests/init/feature.py
tests/todos/__init__.py
tests/todos/action.py
tests/todos/constants.py
tests/todos/feature.py
tests/todos/reducer.py
tests/todos/state.py
tests/todos/test_action.py
tests/todos/test_feature.py
tests/todos/test_todos_reducer.py
tests/todos/todo_reducer.py
tests/todos/visibility_reducer.py
redux_py-0.1.12.dist-info/LICENSE
redux_py-0.1.12.dist-info/METADATA
redux_py-0.1.12.dist-info/WHEEL
redux_py-0.1.12.dist-info/top_level.txt
redux_py-0.1.12.dist-info/RECORD
