Metadata-Version: 2.1
Name: redux-py
Version: 0.1.12
Summary: Redux implementation for Python
Home-page: https://github.com/Carsten-Leue/ReduxPY
Author: Dr. Carsten Leue
Author-email: carsten.leue@gmail.com
License: MIT
Platform: UNKNOWN
Classifier: License :: OSI Approved :: MIT License
Classifier: Programming Language :: Python :: 3.6
Classifier: Programming Language :: Python :: 3.7
Classifier: Programming Language :: Python :: 3.8
Classifier: Programming Language :: Python :: 3.9
Classifier: Programming Language :: Python :: 3
Classifier: Typing :: Typed
Requires-Dist: rx
